MANIFEST.in
README.rst
setup.cfg
setup.py
versioneer.py
eoio/__init__.py
eoio/_version.py
eoio.egg-info/PKG-INFO
eoio.egg-info/SOURCES.txt
eoio.egg-info/dependency_links.txt
eoio.egg-info/requires.txt
eoio.egg-info/top_level.txt
eoio/readers/example_reader_structure.py
eoio/readers/netcdf_reader_test.py
eoio/readers/tests3reader.py
eoio/submodule_template/__init__.py
eoio/submodule_template/class_template.py
eoio/submodule_template/tests/__init__.py
eoio/submodule_template/tests/test_class_template.py
tests/test_sample.py