Metadata-Version: 2.1
Name: eoio
Version: 0.0
Summary: Data readers and preprocessing for satellite data
Home-page: https://gitlab.npl.co.uk/eco/tools/eoio
Author: Mattea Goalen
Author-email: mattea.goalen@npl.co.uk
License: None
Classifier: Development Status :: 2 - Pre-Alpha
Classifier: Programming Language :: Python
Classifier: Programming Language :: Python :: 3.6
Classifier: Programming Language :: Python :: 3.7
Classifier: Programming Language :: Python :: 3.8
Provides-Extra: dev
